README.rst
setup.py
oneplatform/__init__.py
oneplatform/oneid/__about__.py
oneplatform/oneid/__init__.py
oneplatform/oneid/api.py
pyoneplatform.egg-info/PKG-INFO
pyoneplatform.egg-info/SOURCES.txt
pyoneplatform.egg-info/dependency_links.txt
pyoneplatform.egg-info/requires.txt
pyoneplatform.egg-info/top_level.txt