Metadata-Version: 1.2
Name: pyoneplatform
Version: 0.1.3
Summary: OnePlatform API SDK for Python
Home-page: https://github.com/inetspa/oneplatform-sdk-python
Author: INET-SDI
Author-email: inet-sdi@inet.co.th
Maintainer: INET-SDI
Maintainer-email: inet-sdi@inet.co.th
License: GNU GPL 3.0
Platform: UNKNOWN
